setup.py
django_request_tracker.egg-info/PKG-INFO
django_request_tracker.egg-info/SOURCES.txt
django_request_tracker.egg-info/dependency_links.txt
django_request_tracker.egg-info/top_level.txt
tracker/__init__.py
tracker/backends.py
tracker/middleware.py
tracker/models.py
tracker/settings.py
tracker/tests.py
tracker/utils.py