Metadata-Version: 1.0
Name: django-request-tracker
Version: 0.1.0
Summary: Track incoming requests using analytic services.
Home-page: https://github.com/eofs/django-request-tracker
Author: Tomi Pajunen
Author-email: tomi@madlab.fi
License: BSD
Platform: UNKNOWN
